{"cameraMode":{"drawMode":0,"name":"Shaded","section":"Shading Mode"},"sceneLighting":true,"audioPlay":false,"sceneViewState":{"m_AlwaysRefresh":false,"showFog":true,"showSkybox":true,"showFlares":true,"showImageEffects":true,"showParticleSystems":true,"showVisualEffectGraphs":true,"m_FxEnabled":true},"in2DMode":false,"pivot":{"x":1.8853402137756348,"y":11.56668758392334,"z":-386.7818298339844},"rotation":{"x":0.2770047187805176,"y":-0.48868241906166079,"z":0.16705553233623506,"w":0.8103000521659851},"size":0.13746173679828645,"orthographic":false}